vedirect_m8/__init__.py
vedirect_m8/exceptions.py
vedirect_m8/packet_stats.py
vedirect_m8/serconnect.py
vedirect_m8/sertest.py
vedirect_m8/serutils.py
vedirect_m8/ve_controller.py
vedirect_m8/vedirect.py
vedirect_m8/vedirectsim.py
vedirect_m8/vepackets_app.py
vedirect_m8/version.py
vedirect_m8/sim_data/bluesolar_1.23.dump
vedirect_m8/sim_data/bmv702.dump
vedirect_m8/sim_data/smartsolar_1.39.dump
vedirect_m8-1.3.4.dist-info/LICENSE
vedirect_m8-1.3.4.dist-info/METADATA
vedirect_m8-1.3.4.dist-info/WHEEL
vedirect_m8-1.3.4.dist-info/top_level.txt
vedirect_m8-1.3.4.dist-info/RECORD
