Metadata-Version: 2.1
Name: vedirect_m8
Version: 1.3.4
Summary: Victron VE.Direct decoder for Python
Home-page: https://github.com/mano8/vedirect_m8
Author: Janne Kario, Eli Serra
Author-email: eli.serra173@gmail.com
License: MIT
Classifier: License :: OSI Approved :: MIT License
Classifier: Programming Language :: Python :: 3
Classifier: Programming Language :: Python :: 3.7
Classifier: Programming Language :: Python :: 3.8
Classifier: Programming Language :: Python :: 3.9
Classifier: Programming Language :: Python :: 3.10
Classifier: Programming Language :: Python :: 3.11
Requires-Python: >3.5.2
License-File: LICENSE
Requires-Dist: pyserial >=3.5
Requires-Dist: ve-utils >=2.5.3
Provides-Extra: mqtt
Requires-Dist: paho-mqtt >=1.6.1 ; extra == 'mqtt'
Provides-Extra: test
Requires-Dist: pytest >=8.3.2 ; extra == 'test'
Requires-Dist: pytest-cov >=5.0.0 ; extra == 'test'
Requires-Dist: coverage >=7.6.1 ; extra == 'test'
